{"success":true,"data":{"web":[{"url":"https://docs.dify.ai/en/use-dify/nodes/http-request","title":"HTTP Request","description":"The HTTP Request node connects your workflow to external APIs and web services. ... The HTTP Request node automatically detects file responses using ...","position":1,"markdown":"[Skip to main content](https://docs.dify.ai/en/use-dify/nodes/http-request#content-area)\n\n[Dify Docs home page![light logo](https://assets-docs.dify.ai/2025/05/d05cfc6ebe48f725d171dc71c64a5d16.svg)![dark logo](https://assets-docs.dify.ai/2025/05/c51f1cda47c1d9a4a162d7736f6e4c53.svg)](https://docs.dify.ai/en/use-dify/getting-started/introduction)\n\nLatest\n![US](https://d3gk2c5xim1je2.cloudfront.net/flags/US.svg)\n\nEnglish\n\nSearch...\n\nCtrl K\n\nSearch...\n\nNavigation\n\nNodes\n\nHTTP Request\n\nThe HTTP Request node connects your workflow to external APIs and web services. Use it to fetch data, send webhooks, upload files, or integrate with any service that accepts HTTP requests.\n\n![HTTP Request node interface](https://assets-docs.dify.ai/dify-enterprise-mintlify/en/guides/workflow/node/07c5e952eb4c9d6a32d0b7c2d855d4a5.png)\n\nHTTP Request node configuration\n\n## [​](https://docs.dify.ai/en/use-dify/nodes/http-request\\#http-methods)  HTTP Methods\n\nThe node supports all standard HTTP methods for different types of operations:\n\n- Data Retrieval\n\n- Data Submission\n\n- Resource Management\n\n\n**GET** retrieves data from servers without modifying anything. Use for fetching user profiles, searching databases, or getting current status.**HEAD** gets response headers without the full response body. Useful for checking if resources exist or getting metadata.\n\n**POST** sends data to servers, typically for creating new resources. Use for form submissions, file uploads, or sending JSON payloads.**PUT** creates or completely replaces resources. Use when you want to set the entire state of a resource.**PATCH** makes partial updates to existing resources. Use when you only need to modify specific fields.\n\n**DELETE** removes resources from servers. Use for deleting files, user accounts, or any resource that should be removed.\n\n## [​](https://docs.dify.ai/en/use-dify/nodes/http-request\\#configuration)  Configuration\n\nConfigure every aspect of your HTTP request including URL, headers, query parameters, request body, and authentication. Variables from previous workflow nodes can be dynamically inserted anywhere in your request configuration.\n\n### [​](https://docs.dify.ai/en/use-dify/nodes/http-request\\#variable-substitution)  Variable Substitution\n\nReference workflow variables using double curly braces: `{{variable_name}}`. Dify supports deep object access, so you can extract nested values like `{{api_response.data.items[0].id}}` from previous HTTP responses.\n\n### [​](https://docs.dify.ai/en/use-dify/nodes/http-request\\#timeout-configuration)  Timeout Configuration\n\nHTTP requests have configurable timeouts to prevent hanging:\n\n- **Connect timeout**: Maximum time to establish connection (default varies by deployment)\n- **Read timeout**: Maximum time to read response data\n- **Write timeout**: Maximum time to send request data\n\nTimeouts are enforced to maintain workflow performance and prevent resource exhaustion.\n\n### [​](https://docs.dify.ai/en/use-dify/nodes/http-request\\#authentication)  Authentication\n\nThe node supports multiple authentication types:**No Auth** (`type: \"no-auth\"`) \\- No authentication headers added**API Key** (`type: \"api-key\"`) with three subtypes:\n\n- **Basic** (`type: \"basic\"`) \\- Adds Basic Auth header with base64 encoding\n- **Bearer** (`type: \"bearer\"`) \\- Adds `Authorization: Bearer <token>` header\n- **Custom** (`type: \"custom\"`) \\- Adds custom header with specified name and value\n\n### [​](https://docs.dify.ai/en/use-dify/nodes/http-request\\#request-body)  Request Body\n\nChoose the appropriate body type based on your API requirements:\n\n- **JSON** for structured data\n- **Form Data** for traditional web forms\n- **Binary** for file uploads\n- **Raw Text** for custom content types\n\n## [​](https://docs.dify.ai/en/use-dify/nodes/http-request\\#file-detection)  File Detection\n\nThe HTTP Request node automatically detects file responses using sophisticated logic:\n\n1. **Content-Disposition analysis** \\- Checks for `attachment` disposition or filename parameters\n2. **MIME type evaluation** \\- Analyzes content types to distinguish text from binary\n3. **Content sampling** \\- For ambiguous types, samples first 1024 bytes to detect text patterns\n\nText-based responses (JSON, XML, HTML, etc.) are treated as regular data, while binary content becomes file variables.\n\n## [​](https://docs.dify.ai/en/use-dify/nodes/http-request\\#file-operations)  File Operations\n\nThe HTTP Request node handles file uploads and downloads seamlessly:\n\n![HTTP node file upload](https://assets-docs.dify.ai/dify-enterprise-mintlify/en/guides/workflow/node/1f2e33cf7bed33096b5aee145006193d.png)\n\nFile upload configuration example\n\n**File Uploads** use the binary request body option. Select file variables from previous nodes to send files to external services for document storage, media processing, or backup.**File Downloads** are automatically handled when responses contain file content. Downloaded files become available as file variables for use in downstream nodes.\n\n## [​](https://docs.dify.ai/en/use-dify/nodes/http-request\\#error-handling-and-retries)  Error Handling and Retries\n\nConfigure robust error handling for production workflows that depend on external services:\n\n![HTTP retry settings](https://assets-docs.dify.ai/2024/12/2e7c6080c0875e31a074c2a9a4543797.png)\n\nHTTP retry configuration\n\n**Retry Settings** automatically retry failed requests up to 10 times with configurable intervals (maximum 5000ms). This handles temporary network issues or service unavailability.\n\n![HTTP error handling](https://assets-docs.dify.ai/2024/12/91daa86d9770390ab2a41d6d0b6ed1e7.png)\n\nHTTP error handling options\n\n**Error Handling** defines alternative workflow paths when HTTP requests fail, ensuring your workflow continues executing even when external APIs are unavailable.\n\n## [​](https://docs.dify.ai/en/use-dify/nodes/http-request\\#response-processing)  Response Processing\n\nHTTP responses become structured variables in subsequent nodes with separate access to:\n\n- **Response Body** \\- The main content returned by the API\n- **Status Code** \\- HTTP status for conditional logic\n- **Headers** \\- Response metadata as key-value pairs\n- **Files** \\- Any file content returned by the API\n- **Size Information** \\- Content size in bytes with readable formatting (KB/MB)\n\n### [​](https://docs.dify.ai/en/use-dify/nodes/http-request\\#ssl-verification)  SSL Verification\n\nSSL certificate verification is configurable per node (`ssl_verify` parameter). This allows connections to internal services with self-signed certificates while maintaining security for external APIs.\n\n![Customer Feedback Classification workflow](https://assets-docs.dify.ai/dify-enterprise-mintlify/en/guides/workflow/node/090975269f8998f906c5636dde8d9540.png)\n\nDynamic API integration example workflow\n\nWas this page helpful?\n\nYesNo\n\n[Previous](https://docs.dify.ai/en/use-dify/nodes/parameter-extractor) [List OperatorFilter, sort, and select elements from arrays\\\\\n\\\\\nNext](https://docs.dify.ai/en/use-dify/nodes/list-operator)\n\nCtrl+I\n\nOn this page\n\n- [HTTP Methods](https://docs.dify.ai/en/use-dify/nodes/http-request#http-methods)\n- [Configuration](https://docs.dify.ai/en/use-dify/nodes/http-request#configuration)\n- [Variable Substitution](https://docs.dify.ai/en/use-dify/nodes/http-request#variable-substitution)\n- [Timeout Configuration](https://docs.dify.ai/en/use-dify/nodes/http-request#timeout-configuration)\n- [Authentication](https://docs.dify.ai/en/use-dify/nodes/http-request#authentication)\n- [Request Body](https://docs.dify.ai/en/use-dify/nodes/http-request#request-body)\n- [File Detection](https://docs.dify.ai/en/use-dify/nodes/http-request#file-detection)\n- [File Operations](https://docs.dify.ai/en/use-dify/nodes/http-request#file-operations)\n- [Error Handling and Retries](https://docs.dify.ai/en/use-dify/nodes/http-request#error-handling-and-retries)\n- [Response Processing](https://docs.dify.ai/en/use-dify/nodes/http-request#response-processing)\n- [SSL Verification](https://docs.dify.ai/en/use-dify/nodes/http-request#ssl-verification)\n\n![HTTP Request node interface](https://assets-docs.dify.ai/dify-enterprise-mintlify/en/guides/workflow/node/07c5e952eb4c9d6a32d0b7c2d855d4a5.png)\n\n![HTTP node file upload](https://assets-docs.dify.ai/dify-enterprise-mintlify/en/guides/workflow/node/1f2e33cf7bed33096b5aee145006193d.png)\n\n![HTTP retry settings](https://assets-docs.dify.ai/2024/12/2e7c6080c0875e31a074c2a9a4543797.png)\n\n![HTTP error handling](https://assets-docs.dify.ai/2024/12/91daa86d9770390ab2a41d6d0b6ed1e7.png)\n\n![Customer Feedback Classification workflow](https://assets-docs.dify.ai/dify-enterprise-mintlify/en/guides/workflow/node/090975269f8998f906c5636dde8d9540.png)","metadata":{"twitter:card":"summary_large_image","og:site_name":"Dify Docs","og:title":"HTTP Request - Dify Docs","ogTitle":"HTTP Request - Dify Docs","title":"HTTP Request - Dify Docs","apple-mobile-web-app-title":"Dify Docs","og:image":"https://dify-6c0370d8.mintlify.app/mintlify-assets/_next/image?url=%2F_mintlify%2Fapi%2Fog%3Fdivision%3DNodes%26title%3DHTTP%2BRequest%26description%3DConnect%2Bto%2Bexternal%2BAPIs%2Band%2Bweb%2Bservices%26logoLight%3Dhttps%253A%252F%252Fassets-docs.dify.ai%252F2025%252F05%252Fd05cfc6ebe48f725d171dc71c64a5d16.svg%26logoDark%3Dhttps%253A%252F%252Fassets-docs.dify.ai%252F2025%252F05%252Fc51f1cda47c1d9a4a162d7736f6e4c53.svg%26primaryColor%3D%25230060FF%26lightColor%3D%2523688FE8%26darkColor%3D%25230034FF%26backgroundLight%3D%2523ffffff%26backgroundDark%3D%25230b0c0f&w=1200&q=100","ogUrl":"https://docs.dify.ai/en/use-dify/nodes/http-request","msapplication-config":"/mintlify-assets/_mintlify/favicons/dify-6c0370d8/tWYYD8GkT0MUJV0z/_generated/favicon/browserconfig.xml","generator":"Mintlify","ogImage":"https://dify-6c0370d8.mintlify.app/mintlify-assets/_next/image?url=%2F_mintlify%2Fapi%2Fog%3Fdivision%3DNodes%26title%3DHTTP%2BRequest%26description%3DConnect%2Bto%2Bexternal%2BAPIs%2Band%2Bweb%2Bservices%26logoLight%3Dhttps%253A%252F%252Fassets-docs.dify.ai%252F2025%252F05%252Fd05cfc6ebe48f725d171dc71c64a5d16.svg%26logoDark%3Dhttps%253A%252F%252Fassets-docs.dify.ai%252F2025%252F05%252Fc51f1cda47c1d9a4a162d7736f6e4c53.svg%26primaryColor%3D%25230060FF%26lightColor%3D%2523688FE8%26darkColor%3D%25230034FF%26backgroundLight%3D%2523ffffff%26backgroundDark%3D%25230b0c0f&w=1200&q=100","next-size-adjust":"","viewport":"width=device-width, initial-scale=1, maximum-scale=1, viewport-fit=cover","msapplication-TileColor":"#0060FF","og:description":"Connect to external APIs and web services","og:url":"https://docs.dify.ai/en/use-dify/nodes/http-request","og:type":"website","twitter:title":"HTTP Request - Dify Docs","twitter:description":"Connect to external APIs and web services","og:image:height":"630","language":"en","description":"Connect to external APIs and web services","charset":"utf-8","twitter:image":"https://dify-6c0370d8.mintlify.app/mintlify-assets/_next/image?url=%2F_mintlify%2Fapi%2Fog%3Fdivision%3DNodes%26title%3DHTTP%2BRequest%26description%3DConnect%2Bto%2Bexternal%2BAPIs%2Band%2Bweb%2Bservices%26logoLight%3Dhttps%253A%252F%252Fassets-docs.dify.ai%252F2025%252F05%252Fd05cfc6ebe48f725d171dc71c64a5d16.svg%26logoDark%3Dhttps%253A%252F%252Fassets-docs.dify.ai%252F2025%252F05%252Fc51f1cda47c1d9a4a162d7736f6e4c53.svg%26primaryColor%3D%25230060FF%26lightColor%3D%2523688FE8%26darkColor%3D%25230034FF%26backgroundLight%3D%2523ffffff%26backgroundDark%3D%25230b0c0f&w=1200&q=100","og:image:width":"1200","application-name":"Dify Docs","twitter:image:width":"1200","canonical":"https://docs.dify.ai/en/use-dify/nodes/http-request","twitter:image:height":"630","ogDescription":"Connect to external APIs and web services","favicon":"https://docs.dify.ai/mintlify-assets/_mintlify/favicons/dify-6c0370d8/tWYYD8GkT0MUJV0z/_generated/favicon/favicon-16x16.png","scrapeId":"019d01ae-9244-72b1-85e1-2d1dab6c3a81","sourceURL":"https://docs.dify.ai/en/use-dify/nodes/http-request","url":"https://docs.dify.ai/en/use-dify/nodes/http-request","statusCode":200,"contentType":"text/html; charset=utf-8","proxyUsed":"basic","cacheState":"hit","cachedAt":"2026-03-18T06:50:26.405Z","creditsUsed":1}},{"url":"https://docs.dify.ai/versions/3-0-x/en/user-guide/workflow/node/http-request","title":"HTTP Request","description":"This node supports common HTTP request methods: GET: Used to request the server to send a specific resource. POST: Used to submit data to the server, typically ...","position":2,"markdown":"[Skip to main content](https://docs.dify.ai/versions/3-0-x/en/user-guide/workflow/node/http-request#content-area)\n\n[Dify Docs home page![light logo](https://assets-docs.dify.ai/2025/05/d05cfc6ebe48f725d171dc71c64a5d16.svg)![dark logo](https://assets-docs.dify.ai/2025/05/c51f1cda47c1d9a4a162d7736f6e4c53.svg)](https://docs.dify.ai/en/use-dify/getting-started/introduction)\n\nLatest\n![US](https://d3gk2c5xim1je2.cloudfront.net/flags/US.svg)\n\nEnglish\n\nSearch...\n\nCtrl K\n\nSearch...\n\nNavigation\n\nHTTP Request\n\n### [​](https://docs.dify.ai/versions/3-0-x/en/user-guide/workflow/node/http-request\\#definition)  Definition\n\nAllows sending server requests via the HTTP protocol, suitable for scenarios such as retrieving external data, webhooks, generating images, and downloading files. It enables you to send customized HTTP requests to specified web addresses, achieving interconnectivity with various external services.This node supports common HTTP request methods:\n\n- **GET**: Used to request the server to send a specific resource.\n- **POST**: Used to submit data to the server, typically for submitting forms or uploading files.\n- **HEAD**: Similar to GET requests, but the server only returns the response headers without the resource body.\n- **PATCH**: Used to apply partial modifications to a resource.\n- **PUT**: Used to upload resources to the server, typically for updating an existing resource or creating a new one.\n- **DELETE**: Used to request the server to delete a specified resource.\n\nYou can configure various aspects of the HTTP request, including URL, request headers, query parameters, request body content, and authentication information.\n\n![](https://assets-docs.dify.ai/dify-enterprise-mintlify/en/guides/workflow/node/07c5e952eb4c9d6a32d0b7c2d855d4a5.png)\n\n* * *\n\n### [​](https://docs.dify.ai/versions/3-0-x/en/user-guide/workflow/node/http-request\\#scenarios)  Scenarios\n\n- **Send Application Interaction Content to a Specific Server**\n\nOne practical feature of this node is the ability to dynamically insert variables into different parts of the request based on the scenario. For example, when handling customer feedback requests, you can embed variables such as username or customer ID, feedback content, etc., into the request to customize automated reply messages or fetch specific customer information and send related resources to a designated server.![Customer Feedback Classification](https://assets-docs.dify.ai/dify-enterprise-mintlify/en/guides/workflow/node/090975269f8998f906c5636dde8d9540.png)The return values of an HTTP request include the response body, status code, response headers, and files. Notably, if the response contains a file, this node can automatically save the file for use in subsequent steps of the workflow. This design not only improves processing efficiency but also makes handling responses with files straightforward and direct.\n\n- **Send File**\n\nYou can use an HTTP PUT request to send files from the application to other API services. In the request body, you can select the file variable within the `binary`. This method is commonly used in scenarios such as file transfer, document storage, or media processing.Example: Suppose you are developing a document management application and need to send a user-uploaded PDF file to a third-party service. You can use an HTTP request node to pass the file variable.Here is a configuration example:![http-node-send-file](https://assets-docs.dify.ai/dify-enterprise-mintlify/en/guides/workflow/node/1f2e33cf7bed33096b5aee145006193d.png)\n\n### [​](https://docs.dify.ai/versions/3-0-x/en/user-guide/workflow/node/http-request\\#advanced-features)  Advanced Features\n\n**Retry on Failure**For some exceptions that occur in the node, it is usually sufficient to retry the node again. When the error retry function is enabled, the node will automatically retry according to the preset strategy when an error occurs. You can adjust the maximum number of retries and the interval between each retry to set the retry strategy.\n\n- The maximum number of retries is 10\n- The maximum retry interval is 5000 ms\n\n![](https://assets-docs.dify.ai/2024/12/2e7c6080c0875e31a074c2a9a4543797.png)**Error Handling**When processing information, HTTP nodes may encounter exceptional situations such as network request timeouts or request limits. Application developers can follow these steps to configure fail branches, enabling contingency plans when nodes encounter exceptions and avoiding workflow interruptions.\n\n1. Enable “Error Handling” in the HTTP node\n2. Select and configure an error handling strategy\n\nFor more information about exception handling approaches, please refer to [Error Handling](https://docs.dify.ai/en/guides/workflow/error-handling).![](https://assets-docs.dify.ai/2024/12/91daa86d9770390ab2a41d6d0b6ed1e7.png)\n\nWas this page helpful?\n\nYesNo\n\nCtrl+I\n\nOn this page\n\n- [Definition](https://docs.dify.ai/versions/3-0-x/en/user-guide/workflow/node/http-request#definition)\n- [Scenarios](https://docs.dify.ai/versions/3-0-x/en/user-guide/workflow/node/http-request#scenarios)\n- [Advanced Features](https://docs.dify.ai/versions/3-0-x/en/user-guide/workflow/node/http-request#advanced-features)\n\n![](https://assets-docs.dify.ai/dify-enterprise-mintlify/en/guides/workflow/node/07c5e952eb4c9d6a32d0b7c2d855d4a5.png)\n\n![Customer Feedback Classification](https://assets-docs.dify.ai/dify-enterprise-mintlify/en/guides/workflow/node/090975269f8998f906c5636dde8d9540.png)\n\n![http-node-send-file](https://assets-docs.dify.ai/dify-enterprise-mintlify/en/guides/workflow/node/1f2e33cf7bed33096b5aee145006193d.png)\n\n![](https://assets-docs.dify.ai/2024/12/2e7c6080c0875e31a074c2a9a4543797.png)\n\n![](https://assets-docs.dify.ai/2024/12/91daa86d9770390ab2a41d6d0b6ed1e7.png)","metadata":{"title":"HTTP Request - Dify Docs","msapplication-config":"/mintlify-assets/_mintlify/favicons/dify-6c0370d8/tWYYD8GkT0MUJV0z/_generated/favicon/browserconfig.xml","ogTitle":"HTTP Request - Dify Docs","generator":"Mintlify","og:title":"HTTP Request - Dify Docs","og:url":"https://docs.dify.ai/versions/3-0-x/en/user-guide/workflow/node/http-request","og:image":"https://dify-6c0370d8.mintlify.app/mintlify-assets/_next/image?url=%2F_mintlify%2Fapi%2Fog%3Fdivision%3DDocumentation%26title%3DHTTP%2BRequest%26logoLight%3Dhttps%253A%252F%252Fassets-docs.dify.ai%252F2025%252F05%252Fd05cfc6ebe48f725d171dc71c64a5d16.svg%26logoDark%3Dhttps%253A%252F%252Fassets-docs.dify.ai%252F2025%252F05%252Fc51f1cda47c1d9a4a162d7736f6e4c53.svg%26primaryColor%3D%25230060FF%26lightColor%3D%2523688FE8%26darkColor%3D%25230034FF%26backgroundLight%3D%2523ffffff%26backgroundDark%3D%25230b0c0f&w=1200&q=100","og:site_name":"Dify Docs","og:image:height":"630","twitter:title":"HTTP Request - Dify Docs","twitter:image":"https://dify-6c0370d8.mintlify.app/mintlify-assets/_next/image?url=%2F_mintlify%2Fapi%2Fog%3Fdivision%3DDocumentation%26title%3DHTTP%2BRequest%26logoLight%3Dhttps%253A%252F%252Fassets-docs.dify.ai%252F2025%252F05%252Fd05cfc6ebe48f725d171dc71c64a5d16.svg%26logoDark%3Dhttps%253A%252F%252Fassets-docs.dify.ai%252F2025%252F05%252Fc51f1cda47c1d9a4a162d7736f6e4c53.svg%26primaryColor%3D%25230060FF%26lightColor%3D%2523688FE8%26darkColor%3D%25230034FF%26backgroundLight%3D%2523ffffff%26backgroundDark%3D%25230b0c0f&w=1200&q=100","twitter:image:height":"630","charset":"utf-8","application-name":"Dify Docs","msapplication-TileColor":"#0060FF","og:type":"website","twitter:card":"summary_large_image","canonical":"https://docs.dify.ai/versions/3-0-x/en/user-guide/workflow/node/http-request","ogImage":"https://dify-6c0370d8.mintlify.app/mintlify-assets/_next/image?url=%2F_mintlify%2Fapi%2Fog%3Fdivision%3DDocumentation%26title%3DHTTP%2BRequest%26logoLight%3Dhttps%253A%252F%252Fassets-docs.dify.ai%252F2025%252F05%252Fd05cfc6ebe48f725d171dc71c64a5d16.svg%26logoDark%3Dhttps%253A%252F%252Fassets-docs.dify.ai%252F2025%252F05%252Fc51f1cda47c1d9a4a162d7736f6e4c53.svg%26primaryColor%3D%25230060FF%26lightColor%3D%2523688FE8%26darkColor%3D%25230034FF%26backgroundLight%3D%2523ffffff%26backgroundDark%3D%25230b0c0f&w=1200&q=100","language":"en","ogUrl":"https://docs.dify.ai/versions/3-0-x/en/user-guide/workflow/node/http-request","viewport":"width=device-width, initial-scale=1, maximum-scale=1, viewport-fit=cover","og:image:width":"1200","twitter:image:width":"1200","apple-mobile-web-app-title":"Dify Docs","next-size-adjust":"","favicon":"https://docs.dify.ai/mintlify-assets/_mintlify/favicons/dify-6c0370d8/tWYYD8GkT0MUJV0z/_generated/favicon/favicon-16x16.png","scrapeId":"019d01ae-9245-721c-bf40-03f2ca4bf8da","sourceURL":"https://docs.dify.ai/versions/3-0-x/en/user-guide/workflow/node/http-request","url":"https://docs.dify.ai/versions/3-0-x/en/user-guide/workflow/node/http-request","statusCode":200,"contentType":"text/html; charset=utf-8","timezone":"America/New_York","proxyUsed":"basic","cacheState":"miss","indexId":"351394a4-a125-4f32-bf14-955f5b6b3c4a","creditsUsed":1}},{"url":"https://docs.dify.ai/versions/3-0-x/en/user-guide/workflow/node/code","title":"Code","description":"The Code node allows you to embed custom Python or JavaScript scripts into your workflow to manipulate variables in ways that built-in nodes cannot achieve. It ...","position":3,"markdown":"[Skip to main content](https://docs.dify.ai/versions/3-0-x/en/user-guide/workflow/node/code#content-area)\n\n[Dify Docs home page![light logo](https://assets-docs.dify.ai/2025/05/d05cfc6ebe48f725d171dc71c64a5d16.svg)![dark logo](https://assets-docs.dify.ai/2025/05/c51f1cda47c1d9a4a162d7736f6e4c53.svg)](https://docs.dify.ai/)\n\n3.7.x (Enterprise)\n![US](https://d3gk2c5xim1je2.cloudfront.net/flags/US.svg)\n\nEnglish\n\nSearch...\n\nCtrl K\n\nSearch...\n\nNavigation\n\nNode Description\n\nCode\n\n## [​](https://docs.dify.ai/versions/3-0-x/en/user-guide/workflow/node/code\\#introduction)  Introduction\n\nThe Code node allows you to embed custom Python or JavaScript scripts into your workflow to manipulate variables in ways that built-in nodes cannot achieve. It can simplify your workflow and is suitable for scenarios such as arithmetic operations, JSON transformations, text processing, and more.To use variables from other nodes in a Code node, you must select them in the `Input Variables` field and then reference them in your code.![](https://assets-docs.dify.ai/dify-enterprise-mintlify/en/guides/workflow/node/9969aa1bc1912aebe366f5d8f5dde296.png)\n\n## [​](https://docs.dify.ai/versions/3-0-x/en/user-guide/workflow/node/code\\#what-a-code-node-can-do)  What a Code Node Can Do\n\nWith the Code node, you can perform common operations such as structured data processing, mathematical calculations, and data concatenation.\n\n### [​](https://docs.dify.ai/versions/3-0-x/en/user-guide/workflow/node/code\\#structured-data-processing)  Structured Data Processing\n\nIn workflows, you often have to deal with unstructured data processing, such as parsing, extracting, and transforming JSON strings.A typical example is data processing from an HTTP node: in common API return structures, data may be nested within multiple layers of JSON objects, and you need to extract certain fields. The Code node can help you perform these operations.Here is a simple example that extracts the `data.name` field from a JSON string returned by an HTTP node:\n\nCopy\n\n```\ndef main(http_response: str) -> dict:\n    import json\n    data = json.loads(http_response)\n    return {\n        # Note to declare 'result' in the output variables\n        'result': data['data']['name']\n    }\n```\n\n### [​](https://docs.dify.ai/versions/3-0-x/en/user-guide/workflow/node/code\\#mathematical-calculations)  Mathematical Calculations\n\nWhen you need to perform complex mathematical calculations in a workflow, you can also use the Code node. For example, calculating a complex mathematical formula or performing some statistical analysis on data.Here is a simple example that calculates the variance of an array:\n\nCopy\n\n```\ndef main(x: list) -> dict:\n    return {\n        # Note to declare 'result' in the output variables\n        'result': sum([(i - sum(x) / len(x)) ** 2 for i in x]) / len(x)\n    }\n```\n\n### [​](https://docs.dify.ai/versions/3-0-x/en/user-guide/workflow/node/code\\#data-concatenation)  Data Concatenation\n\nSometimes you may need to concatenate multiple data sources, such as multiple knowledge retrievals, data searches, API calls, etc. The Code node can help you integrate these data sources together.Here is a simple example that merges data from two knowledge bases:\n\nCopy\n\n```\ndef main(knowledge1: list, knowledge2: list) -> dict:\n    return {\n        # Note to declare 'result' in the output variables\n        'result': knowledge1 + knowledge2\n    }\n```\n\n## [​](https://docs.dify.ai/versions/3-0-x/en/user-guide/workflow/node/code\\#local-deployment)  Local Deployment\n\nIf you are a local deployment user, you need to start a sandbox service to prevent the execution of malicious code.This sandbox service requires Docker. You can start it directly using `docker-compose`:\n\nCopy\n\n```\ndocker-compose -f docker-compose.middleware.yaml up -d\n```\n\nIf your system has Docker Compose V2 installed, use `docker compose` instead of `docker-compose`. You can check the version with `$ docker compose version`.For more information, see the [official Docker documentation](https://docs.docker.com/compose/#compose-v2-and-the-new-docker-compose-command).\n\nYou can learn more about the sandbox service [here](https://github.com/langgenius/dify/tree/main/docker/docker-compose.middleware.yaml).\n\n## [​](https://docs.dify.ai/versions/3-0-x/en/user-guide/workflow/node/code\\#security-policies)  Security Policies\n\nBoth Python and JavaScript execution environments are strictly isolated (sandboxed) to ensure security. This means that functions that consume large amounts of system resources or may pose security risks are prohibited, such as direct file system access, making network requests, or executing operating system-level commands. These limitations ensure the safe execution of the code while avoiding excessive consumption of system resources.\n\n### [​](https://docs.dify.ai/versions/3-0-x/en/user-guide/workflow/node/code\\#advanced-features)  Advanced Features\n\n#### [​](https://docs.dify.ai/versions/3-0-x/en/user-guide/workflow/node/code\\#retry-on-failure)  Retry on Failure\n\nCertain node errors are transient and can often be resolved by rerunning the node. By enabling the error retry feature, the node will automatically attempt to rerun according to a predefined policy upon failure.You can adjust the maximum number of retries and the interval between each retry to set the retry strategy.\n\n- The maximum number of retries is 10\n- The maximum retry interval is 5000 ms\n\n![](https://assets-docs.dify.ai/2024/12/9fdd5525a91dc925b79b89272893becf.png)\n\n#### [​](https://docs.dify.ai/versions/3-0-x/en/user-guide/workflow/node/code\\#error-handling)  Error Handling\n\nWhen processing information, Code nodes may encounter code execution errors. You can follow these steps to configure error branches. This allows you to enable a contingency plan when an error occurs in the node, preventing the entire workflow from being interrupted.\n\n1. Enable **Error Handling** for the Code node.\n2. Select and configure an error handling strategy.\n\n![Code Error Handling](https://assets-docs.dify.ai/2024/12/58f392734ce44b22cd8c160faf28cd14.png)\n\nFor more information about error handling approaches, see [Error Handling](https://docs.dify.ai/en/guides/workflow/error-handling/README).\n\n### [​](https://docs.dify.ai/versions/3-0-x/en/user-guide/workflow/node/code\\#faq)  FAQ\n\n**Why can’t I save the code it in the Code node?**Check if the code contains potentially dangerous behaviors. For example:\n\nCopy\n\n```\ndef main() -> dict:\n    return {\n        \"result\": open(\"/etc/passwd\").read(),\n    }\n```\n\nThis code snippet has the following issues:\n\n- **Unauthorized file access**: The code attempts to read the `/etc/passwd` file, which is a critical system file in Unix/Linux systems that stores user account information.\n- **Sensitive information disclosure**: The `/etc/passwd` file contains important information about system users, such as usernames, user IDs, group IDs, home directory paths, etc. Direct access could lead to information leakage.\n\nDangerous code will be automatically blocked by Cloudflare WAF. You can check if it’s been blocked by looking at the **Network** tab in your browser’s **Web Developer Tools**.![Cloudflare WAF](https://assets-docs.dify.ai/2024/12/ad4dc065c4c567c150ab7fa7bfd123a3.png)\n\n## [​](https://docs.dify.ai/versions/3-0-x/en/user-guide/workflow/node/code\\#code-fix)  Code Fix\n\nThe **Code Fix** feature enables automatic code fix by leveraging the previous run’s `current_code` and `error_message` variables.When a Code node fails:\n\n- The system captures the code and error message.\n- These are passed into the prompt as context variables.\n- A new version of the code is generated for review and retry.\n\n### [​](https://docs.dify.ai/versions/3-0-x/en/user-guide/workflow/node/code\\#fix-prompt)  Fix Prompt\n\nYou can customize a prompt like:\n\nCopy\n\n```\nFix the following code based on this error message:\n\nCode: {{current_code}}\n\nError: {{error_message}}`\n```\n\nIn the prompt editor, use the variable insertion menu (`/` or `{`) to insert variables.\n\n![Codefix PN](https://mintcdn.com/dify-6c0370d8/7ofzWAXbPyxqXN2g/images/codefix.PNG?fit=max&auto=format&n=7ofzWAXbPyxqXN2g&q=85&s=a92da696fe0fe19d31e5d36584ff5cd2)\n\n### [​](https://docs.dify.ai/versions/3-0-x/en/user-guide/workflow/node/code\\#context-variables)  Context Variables\n\nTo enable automatic code fix, reference the following context variables in your prompt:\n\n- `current_code`: The code from the last run of this node.\n- `error_message`: The error message from the last run if it failed; otherwise, empty.\n\nThese variables are automatically available when the Code node runs, allowing the model to use prior run information for iterative correction.\n\n- The `last_run` variable can be used to reference the input/output of the previous run.\n- In addition to the variable above, you can reference the output variables of any preceding nodes as needed.\n\n### [​](https://docs.dify.ai/versions/3-0-x/en/user-guide/workflow/node/code\\#version-management)  Version Management\n\nVersion management reduces manual copy-paste and allows iterative debugging directly within the workflow.\n\n1. Each correction attempt is saved as a separate version (e.g., Version 1, Version 2).\n2. You can switch between versions via the dropdown in the result display area.\n\nWas this page helpful?\n\nYesNo\n\n[Previous](https://docs.dify.ai/versions/3-0-x/en/user-guide/workflow/node/ifelse) [Template\\\\\n\\\\\nNext](https://docs.dify.ai/versions/3-0-x/en/user-guide/workflow/node/template)\n\nCtrl+I\n\nOn this page\n\n- [Introduction](https://docs.dify.ai/versions/3-0-x/en/user-guide/workflow/node/code#introduction)\n- [What a Code Node Can Do](https://docs.dify.ai/versions/3-0-x/en/user-guide/workflow/node/code#what-a-code-node-can-do)\n- [Structured Data Processing](https://docs.dify.ai/versions/3-0-x/en/user-guide/workflow/node/code#structured-data-processing)\n- [Mathematical Calculations](https://docs.dify.ai/versions/3-0-x/en/user-guide/workflow/node/code#mathematical-calculations)\n- [Data Concatenation](https://docs.dify.ai/versions/3-0-x/en/user-guide/workflow/node/code#data-concatenation)\n- [Local Deployment](https://docs.dify.ai/versions/3-0-x/en/user-guide/workflow/node/code#local-deployment)\n- [Security Policies](https://docs.dify.ai/versions/3-0-x/en/user-guide/workflow/node/code#security-policies)\n- [Advanced Features](https://docs.dify.ai/versions/3-0-x/en/user-guide/workflow/node/code#advanced-features)\n- [Retry on Failure](https://docs.dify.ai/versions/3-0-x/en/user-guide/workflow/node/code#retry-on-failure)\n- [Error Handling](https://docs.dify.ai/versions/3-0-x/en/user-guide/workflow/node/code#error-handling)\n- [FAQ](https://docs.dify.ai/versions/3-0-x/en/user-guide/workflow/node/code#faq)\n- [Code Fix](https://docs.dify.ai/versions/3-0-x/en/user-guide/workflow/node/code#code-fix)\n- [Fix Prompt](https://docs.dify.ai/versions/3-0-x/en/user-guide/workflow/node/code#fix-prompt)\n- [Context Variables](https://docs.dify.ai/versions/3-0-x/en/user-guide/workflow/node/code#context-variables)\n- [Version Management](https://docs.dify.ai/versions/3-0-x/en/user-guide/workflow/node/code#version-management)\n\n![](https://assets-docs.dify.ai/dify-enterprise-mintlify/en/guides/workflow/node/9969aa1bc1912aebe366f5d8f5dde296.png)\n\n![](https://assets-docs.dify.ai/2024/12/9fdd5525a91dc925b79b89272893becf.png)\n\n![Code Error Handling](https://assets-docs.dify.ai/2024/12/58f392734ce44b22cd8c160faf28cd14.png)\n\n![Cloudflare WAF](https://assets-docs.dify.ai/2024/12/ad4dc065c4c567c150ab7fa7bfd123a3.png)\n\n![Codefix PN](https://mintcdn.com/dify-6c0370d8/7ofzWAXbPyxqXN2g/images/codefix.PNG?w=840&fit=max&auto=format&n=7ofzWAXbPyxqXN2g&q=85&s=538cc6b668a4828779fd22eb576e6ae7)","metadata":{"viewport":"width=device-width, initial-scale=1, maximum-scale=1, viewport-fit=cover","next-size-adjust":"","msapplication-TileColor":"#0060FF","title":"Code - Dify Docs","charset":"utf-8","og:site_name":"Dify Docs","og:image:width":"1200","og:image:height":"630","generator":"Mintlify","og:type":"website","twitter:card":"summary_large_image","ogTitle":"Code - Dify Docs","ogImage":"https://dify-6c0370d8.mintlify.app/mintlify-assets/_next/image?url=%2F_mintlify%2Fapi%2Fog%3Fdivision%3DNode%2BDescription%26title%3DCode%26logoLight%3Dhttps%253A%252F%252Fassets-docs.dify.ai%252F2025%252F05%252Fd05cfc6ebe48f725d171dc71c64a5d16.svg%26logoDark%3Dhttps%253A%252F%252Fassets-docs.dify.ai%252F2025%252F05%252Fc51f1cda47c1d9a4a162d7736f6e4c53.svg%26primaryColor%3D%25230060FF%26lightColor%3D%2523688FE8%26darkColor%3D%25230034FF%26backgroundLight%3D%2523ffffff%26backgroundDark%3D%25230b0c0f&w=1200&q=100","language":"en","og:title":"Code - Dify Docs","apple-mobile-web-app-title":"Dify Docs","og:url":"https://docs.dify.ai/versions/3-0-x/en/user-guide/workflow/node/code","twitter:title":"Code - Dify Docs","twitter:image":"https://dify-6c0370d8.mintlify.app/mintlify-assets/_next/image?url=%2F_mintlify%2Fapi%2Fog%3Fdivision%3DNode%2BDescription%26title%3DCode%26logoLight%3Dhttps%253A%252F%252Fassets-docs.dify.ai%252F2025%252F05%252Fd05cfc6ebe48f725d171dc71c64a5d16.svg%26logoDark%3Dhttps%253A%252F%252Fassets-docs.dify.ai%252F2025%252F05%252Fc51f1cda47c1d9a4a162d7736f6e4c53.svg%26primaryColor%3D%25230060FF%26lightColor%3D%2523688FE8%26darkColor%3D%25230034FF%26backgroundLight%3D%2523ffffff%26backgroundDark%3D%25230b0c0f&w=1200&q=100","ogUrl":"https://docs.dify.ai/versions/3-0-x/en/user-guide/workflow/node/code","og:image":"https://dify-6c0370d8.mintlify.app/mintlify-assets/_next/image?url=%2F_mintlify%2Fapi%2Fog%3Fdivision%3DNode%2BDescription%26title%3DCode%26logoLight%3Dhttps%253A%252F%252Fassets-docs.dify.ai%252F2025%252F05%252Fd05cfc6ebe48f725d171dc71c64a5d16.svg%26logoDark%3Dhttps%253A%252F%252Fassets-docs.dify.ai%252F2025%252F05%252Fc51f1cda47c1d9a4a162d7736f6e4c53.svg%26primaryColor%3D%25230060FF%26lightColor%3D%2523688FE8%26darkColor%3D%25230034FF%26backgroundLight%3D%2523ffffff%26backgroundDark%3D%25230b0c0f&w=1200&q=100","application-name":"Dify Docs","twitter:image:width":"1200","twitter:image:height":"630","msapplication-config":"/mintlify-assets/_mintlify/favicons/dify-6c0370d8/tWYYD8GkT0MUJV0z/_generated/favicon/browserconfig.xml","canonical":"https://docs.dify.ai/versions/3-0-x/en/user-guide/workflow/node/code","favicon":"https://docs.dify.ai/mintlify-assets/_mintlify/favicons/dify-6c0370d8/tWYYD8GkT0MUJV0z/_generated/favicon/favicon-16x16.png","scrapeId":"019d01ae-9245-721c-bf40-073067b3aa04","sourceURL":"https://docs.dify.ai/versions/3-0-x/en/user-guide/workflow/node/code","url":"https://docs.dify.ai/versions/3-0-x/en/user-guide/workflow/node/code","statusCode":200,"contentType":"text/html; charset=utf-8","proxyUsed":"basic","cacheState":"hit","cachedAt":"2026-03-16T04:24:12.211Z","creditsUsed":1}}]}}